{
  "Gov-Tech": "GovTech",
  "gov-tech": "GovTech",
  "GovTech": "GovTech",
  "government technology": "GovTech",

  "AI governance": "AI Governance",
  "AIGovernance": "AI Governance",
  "ai governance": "AI Governance",

  "DigitalTwin": "Digital Twin",
  "digital twin": "Digital Twin",
  "数字孪生": "Digital Twin",

  "城市治理": "Urban Governance",
  "urban governance": "Urban Governance",

  "SupplyChain": "Supply Chain",
  "supply chain": "Supply Chain",

  "Geopolitics": "Geopolitics",
  "geopolitics": "Geopolitics"
}
